popxf/validator/__init__.py
popxf/validator/_version.py
popxf/validator/schemas.py
popxf/validator/validator.py
popxf_validator-0.0.1.dist-info/licenses/LICENSE
popxf_validator-0.0.1.dist-info/METADATA
popxf_validator-0.0.1.dist-info/WHEEL
popxf_validator-0.0.1.dist-info/top_level.txt
popxf_validator-0.0.1.dist-info/RECORD
