Metadata-Version: 2.4
Name: popxf-validator
Version: 0.0.1
Summary: Package for validating POPxf files
Author-email: Ken Mimasu <ken.mimasu@soton.ac.uk>, Aleks Smolkovič <aleks.smolkovic@ijs.si>, Peter Stangl <peter.stangl@cern.ch>
License: MIT
Requires-Python: >=3.8
License-File: LICENSE
Requires-Dist: jsonschema
Dynamic: license-file
